[
  {
    "image": "./images/pilsner_cholo_water.png",
    "alt": "Pilsner Glass",
    "name": "Cholo Water",
    "type": "Pilsner...4.9%",
    "description": "Our low ABV, light and crushable bohemian Pilsner.",
    "prices": "16oz...$7 | 5oz...$2 | 32oz Crowler (To-Go)...$14"
  },
  {
    "image": "./images/caramel.png",
    "alt": "Melted Caramel",
    "name": "Mi Morena",
    "type": "Amber Lager...5.4%",
    "description": "Dark, rich lager with hints of caramel",
    "prices": "16oz...$7 | 5oz...$2 | 32oz Crowler (To-Go)...$14"
  },
  {
    "image": "./images/prickly.png",
    "alt": "Prickly Pair",
    "name": "La Pearrona",
    "type": "American Wheat Beer...5.5%",
    "description": "Crisp wheat beer with a slight taste of prickly pear fruit.",
    "prices": "16oz...$7 | 5oz...$2 | 32oz Crowler (To-Go)...$14"
  },
  {
    "image": "./images/firme_lager_barley.png",
    "alt": "Barley",
    "name": "Firme Lager",
    "type": "Mexican Lager...5.3%",
    "description": "A light, refreshing Santa Ana style Mexican Lager.",
    "prices": "16oz...$7 | 5oz...$2 | 32oz Crowler (To-Go)...$14"
  },
  {
    "image": "./images/firme_lager_lime.png",
    "alt": "Lime",
    "name": "Firme Lager W/ Sea Salt & Lime",
    "type": "Mexican Lager...5.3%",
    "description": "Our Santa Ana style Mexican Lager with a touch of lime and sea salt.",
    "prices": "16oz...$7 | 5oz...$2 | 32oz Crowler (To-Go)...$14"
  },
  {
    "image": "./images/tarta_buena_mango.png",
    "alt": "Mango",
    "name": "Tarta Buena",
    "type": "Coconut & Mango Sour...6%",
    "description": "Sweet, tart and bursting with mango and coconut aroma.",
    "prices": "16oz...$7 | 5oz...$2 | 32oz Crowler (To-Go)...$14"
  },
  {
    "image": "./images/fantasma_ghost_chili.png",
    "alt": "Ghost Chili",
    "name": "Fantasma Pale Ale",
    "type": "Ghost Chili Pale Ale...6%",
    "description": "Our Cito Pale Ale with strong, smokey flavor and Ghost Chili spice to heat things up.",
    "prices": "16oz...$7 | 5oz...$2 | 32oz Crowler (To-Go)...$14"
  },
  {
    "image": "./images/pale_ale_hops.png",
    "alt": "Hops",
    "name": "Pale Ale",
    "type": "Pale Ale...6%",
    "description": "This perfect classic pale ale is brewed with Cascade and Laurel hops.",
    "prices": "16oz...$7 | 5oz...$2 | 32oz Crowler (To-Go)...$14"
  },
  {
    "image": "./images/pitaya_dragonfruit.png",
    "alt": "Dragon Fruit",
    "name": "La Pitaya",
    "type": "Dragon Fruit Ale...6.6%",
    "description": "Crisp ale brewed with dragon fruit.",
    "prices": "16oz...$7 | 5oz...$2 | 32oz Crowler (To-Go)...$14"
  },
  {
    "image": "./images/haze_ventura_orange.png",
    "alt": "Orange",
    "name": "Haze Ventura",
    "type": "Hazy IPA...6.6%",
    "description": "Our 100% Citra hopped Hazy IPA.",
    "prices": "16oz...$7 | 5oz...$2 | 32oz Crowler (To-Go)...$14"
  },
  {
    "image": "./images/POG.png",
    "alt": "Guava",
    "name": "The Slammer",
    "type": "POG Seltzer...7%",
    "description": "Our POG (Pineapple, Orange, Guava) Seltzer is deliciously heavy on the citrus aroma but has a dry finish with a touch of sweetness.",
    "prices": "16oz...$7 | 5oz...$2 | 32oz Crowler (To-Go)...$14"
  },
  {
    "image": "./images/theo_hazy_orangeblossom.png",
    "alt": "Orangeblossom",
    "name": "Theo Hazy IPA",
    "type": "Hazy IPA...7.2%",
    "description": "An unfiltered Hazy IPA brewed with El Dorado, Mosaic and Amarillo hops.",
    "prices": "16oz...$7 | 5oz...$2 | 32oz Crowler (To-Go)...$14"
  },
  {
    "image": "./images/wasshop_rockers_hops.png",
    "alt": "Hops",
    "name": "Wasshop Rockers",
    "type": "Double IPA...8.5%",
    "description": "West Coast DIPA brewed with Huell Melon and Southern Cross hops.",
    "prices": "12oz...$7 | 5oz...$3 | 32oz Crowler (To-Go)...$16"
  },
  {
    "image": "./images/holy_not_mole_cinnamon.png",
    "alt": "Cinnamon",
    "name": "Holy Not Mole",
    "type": "Ibarra Mexican Chocolate Stout...8.8%",
    "description": "Brewed with cinnamon, allspice and Ibarra Mexican Chocolate for a smooth, rich taste.",
    "prices": "12oz...$7 | 5oz...$3 | 32oz Crowler (To-Go)...$16"
  },
  {
    "image": "./images/cerveza_cito_logo_padded_2.png",
    "alt": "Cerveza Cito",
    "name": "Flight",
    "type": "Four Tasters",
    "description": "Get a taste of Cerveza Cito. Each flight includes four 5 oz pours of your choice.",
    "prices": "4 x 5oz...$8"
  }
]